rts_package/__init__.py
rts_package/cli_feat_imp.py
rts_package/cli_pred.py
rts_package/cli_uncert_pred.py
rts_package/models/__init__.py
rts_package/models/unet.py
rts_package/models/unet_super.py
rts_package/models/unet_utils.py
rts_package/utils/__init__.py
rts_package/utils/uncertainty.py
root_tissue_seg_package-1.0.7.dist-info/LICENSE
root_tissue_seg_package-1.0.7.dist-info/METADATA
root_tissue_seg_package-1.0.7.dist-info/WHEEL
root_tissue_seg_package-1.0.7.dist-info/entry_points.txt
root_tissue_seg_package-1.0.7.dist-info/top_level.txt
root_tissue_seg_package-1.0.7.dist-info/RECORD
