Metadata-Version: 2.1
Name: root-tissue-seg-package
Version: 1.0.7
Summary: An mlf-core prediction package for root tissue segmentation.
Home-page: https://github.com/qbic-pipelines/rts-prediction-package/
Author: Julian Wanner
Author-email: jwgithub@mailbox.org
License: MIT
Keywords: root tissue segmentation
Platform: UNKNOWN
Classifier: Development Status :: 2 - Pre-Alpha
Classifier: Intended Audience :: Developers
Classifier: License :: OSI Approved :: MIT License
Classifier: Natural Language :: English
Classifier: Programming Language :: Python :: 3
Classifier: Programming Language :: Python :: 3.7
Classifier: Programming Language :: Python :: 3.8
Classifier: Programming Language :: Python :: 3.9
Requires-Python: >=3.7
Requires-Dist: rich (~=10.11.0)
Requires-Dist: click (~=8.0.1)
Requires-Dist: setuptools (~=58.2.0)
Requires-Dist: numpy (~=1.21.2)
Requires-Dist: torch (~=1.9.1)
Requires-Dist: pytorch-lightning (~=1.4.9)
Requires-Dist: torch-optimizer (~=0.1.0)
Requires-Dist: tifffile (~=2021.8.30)
Requires-Dist: PyYAML (~=5.4.1)
Requires-Dist: torchvision (~=0.10.1)
Requires-Dist: torchmetrics (==0.6.0)
Requires-Dist: captum (==0.4.0)
Requires-Dist: alive-progress (==2.4.1)
